xspect/__init__.py
xspect/classify.py
xspect/definitions.py
xspect/download_models.py
xspect/file_io.py
xspect/filter_sequences.py
xspect/main.py
xspect/model_management.py
xspect/train.py
xspect/web.py
xspect/handlers/__init__.py
xspect/handlers/ncbi.py
xspect/handlers/pubmlst.py
xspect/misclassification_detection/__init__.py
xspect/misclassification_detection/mapping.py
xspect/misclassification_detection/point_pattern_analysis.py
xspect/misclassification_detection/simulate_reads.py
xspect/models/__init__.py
xspect/models/mlst_result.py
xspect/models/probabilistic_filter_mlst_model.py
xspect/models/probabilistic_filter_model.py
xspect/models/probabilistic_filter_svm_model.py
xspect/models/probabilistic_single_filter_model.py
xspect/models/result.py
xspect/xspect-web/.gitignore
xspect/xspect-web/README.md
xspect/xspect-web/components.json
xspect/xspect-web/eslint.config.js
xspect/xspect-web/index.html
xspect/xspect-web/package-lock.json
xspect/xspect-web/package.json
xspect/xspect-web/pnpm-lock.yaml
xspect/xspect-web/tsconfig.app.json
xspect/xspect-web/tsconfig.json
xspect/xspect-web/tsconfig.node.json
xspect/xspect-web/vite.config.ts
xspect/xspect-web/dist/index.html
xspect/xspect-web/dist/vite.svg
xspect/xspect-web/dist/assets/index-Bg0QP9Ys.js
xspect/xspect-web/dist/assets/index-Ceo58xui.css
xspect/xspect-web/public/vite.svg
xspect/xspect-web/src/App.tsx
xspect/xspect-web/src/api.tsx
xspect/xspect-web/src/index.css
xspect/xspect-web/src/main.tsx
xspect/xspect-web/src/types.tsx
xspect/xspect-web/src/utils.tsx
xspect/xspect-web/src/vite-env.d.ts
xspect/xspect-web/src/assets/react.svg
xspect/xspect-web/src/components/classification-form.tsx
xspect/xspect-web/src/components/classify.tsx
xspect/xspect-web/src/components/data-table.tsx
xspect/xspect-web/src/components/dropdown-checkboxes.tsx
xspect/xspect-web/src/components/dropdown-slider.tsx
xspect/xspect-web/src/components/filter-form.tsx
xspect/xspect-web/src/components/filter.tsx
xspect-0.7.3.dist-info/licenses/LICENSE
xspect-0.7.3.dist-info/METADATA
xspect-0.7.3.dist-info/WHEEL
xspect-0.7.3.dist-info/entry_points.txt
xspect-0.7.3.dist-info/top_level.txt
xspect-0.7.3.dist-info/RECORD
