Metadata-Version: 2.4
Name: XspecT
Version: 0.7.3
Summary: Tool to monitor and characterize pathogens using Bloom filters.
License: MIT License
Project-URL: Repository, https://github.com/BIONF/XspecT2.git
Classifier: Intended Audience :: Developers
Classifier: Topic :: Scientific/Engineering :: Bio-Informatics
Classifier: License :: OSI Approved :: MIT License
Requires-Python: <3.14,>=3.10
License-File: LICENSE
Requires-Dist: biopython
Requires-Dist: requests
Requires-Dist: scikit-learn
Requires-Dist: Bio
Requires-Dist: loguru
Requires-Dist: click
Requires-Dist: python-slugify
Requires-Dist: cobs-reloaded
Requires-Dist: rbloom
Requires-Dist: xxhash
Requires-Dist: fastapi
Requires-Dist: uvicorn
Requires-Dist: python-multipart
Requires-Dist: mappy
Requires-Dist: pysam
Requires-Dist: numpy
Provides-Extra: docs
Requires-Dist: mkdocs-material; extra == "docs"
Requires-Dist: mkdocs-include-markdown-plugin; extra == "docs"
Provides-Extra: test
Requires-Dist: pytest; extra == "test"
Requires-Dist: pytest-cov; extra == "test"
Requires-Dist: pytest-retry; extra == "test"
Requires-Dist: httpx; extra == "test"
Dynamic: license-file
